{
  "id": "example-02",
  "simulation": {
    "concurrency": 8,
    "simRunsAmount": {
      "base": 20000,
      "bonus": 20000
    },
    "maxPendingSims": 25,
    "maxDiskBuffer": 150,
    "makeUncompressedBooks": false
  },
  "betSimulations": [
    {
      "id": "851cc15e",
      "players": {
        "count": 100,
        "startingBalance": 500
      },
      "betGroups": [
        {
          "id": "53b4e010",
          "mode": "base",
          "betAmount": 1,
          "spins": 500
        },
        {
          "id": "e8a72748",
          "mode": "bonus",
          "betAmount": 1,
          "spins": 15
        }
      ]
    }
  ],
  "reelSets": [],
  "forceStop": false
}